{"schema_version":2.13,"forms":[{"name":"Outras solicitações","is_recursive":1,"icon":"fa fa-square","icon_color":"#999999","background_color":"#e7e7e7","access_rights":1,"description":"Outros chamados não contemplados","content":"","is_active":1,"language":"","helpdesk_home":1,"is_deleted":0,"validation_required":0,"is_default":0,"is_captcha_enabled":0,"show_rule":1,"formanswer_name":"Outras solicitações","is_visible":1,"uuid":"252f708b-8d9ac576-68273a2d29d3d4.21095881","users":[],"groups":[],"profiles":[],"_entity":"CEDEP","_plugin_formcreator_category":"Requisições","_profiles":[],"_users":[],"_groups":[],"_sections":[{"name":"Informações do Usuário","order":1,"show_rule":1,"uuid":"252f708b-8d9ac576-68273a2d2acbe5.65492367","_questions":[{"name":"Para quem será aberto o ticket?","fieldtype":"select","required":1,"show_empty":1,"default_values":null,"itemtype":"","values":"[\"Meu usuário\",\"Outro usuário\"]","description":"&#60;p&#62;Informe se a requisição é para você ou para um terceiro.&#60;/p&#62;","row":0,"col":0,"width":4,"show_rule":1,"uuid":"252f708b-8d9ac576-68273a2d2b1689.00438115","_conditions":[],"_parameters":[]},{"name":"Informe para quem será aberto o ticket","fieldtype":"glpiselect","required":1,"show_empty":1,"default_values":0,"itemtype":"User","values":"{\"entity_restrict\":\"2\"}","description":"","row":1,"col":0,"width":4,"show_rule":2,"uuid":"252f708b-8d9ac576-68273a2d2b7994.82222056","_conditions":[{"itemtype":"PluginFormcreatorQuestion","plugin_formcreator_questions_id":"252f708b-8d9ac576-68273a2d2b1689.00438115","show_condition":1,"show_value":"Outro usuário","show_logic":1,"order":1,"uuid":"252f708b-8d9ac576-68273a2d2ba953.65240960"}],"_parameters":[]}],"_conditions":[]},{"name":"Requisição","order":2,"show_rule":2,"uuid":"252f708b-8d9ac576-68273a2d2c3410.64355476","_questions":[{"name":"Descrição/Justificativa","fieldtype":"textarea","required":1,"show_empty":0,"default_values":"","itemtype":"","values":null,"description":"","row":1,"col":0,"width":4,"show_rule":2,"uuid":"252f708b-8d9ac576-68273a2d2d4110.42993838","_conditions":[{"itemtype":"PluginFormcreatorQuestion","plugin_formcreator_questions_id":"252f708b-8d9ac576-68273a2d2ec115.84967052","show_condition":1,"show_value":"request","show_logic":1,"order":1,"uuid":"252f708b-8d9ac576-68273bfb198fc2.73464351"}],"_parameters":{"textarea":{"regex":{"regex":"","fieldname":"regex","uuid":"252f708b-8d9ac576-68273a2d2e15a2.96617031"},"range":{"range_min":10,"range_max":0,"fieldname":"range","uuid":"252f708b-8d9ac576-68273a2d2e6858.17822610"}}}},{"name":"Tipo da Requisição","fieldtype":"requesttype","required":1,"show_empty":1,"default_values":0,"itemtype":"","values":null,"description":"","row":0,"col":0,"width":4,"show_rule":2,"uuid":"252f708b-8d9ac576-68273a2d2ec115.84967052","_conditions":[{"itemtype":"PluginFormcreatorQuestion","plugin_formcreator_questions_id":"252f708b-8d9ac576-68273a2d2b1689.00438115","show_condition":1,"show_value":"Meu usuário","show_logic":1,"order":1,"uuid":"252f708b-8d9ac576-68273a2d2f0f54.02033627"},{"itemtype":"PluginFormcreatorQuestion","plugin_formcreator_questions_id":"252f708b-8d9ac576-68273a2d2b7994.82222056","show_condition":2,"show_value":"","show_logic":2,"order":2,"uuid":"252f708b-8d9ac576-68273a2d2f5c30.71066557"}],"_parameters":[]},{"name":"Descreva a falha/incidente","fieldtype":"textarea","required":1,"show_empty":0,"default_values":"","itemtype":"","values":null,"description":"&#60;p&#62;Descreva o problema de forma objetiva e clara. &#60;/p&#62;","row":2,"col":0,"width":4,"show_rule":2,"uuid":"252f708b-8d9ac576-68273a2d2fa675.69463119","_conditions":[{"itemtype":"PluginFormcreatorQuestion","plugin_formcreator_questions_id":"252f708b-8d9ac576-68273a2d2ec115.84967052","show_condition":1,"show_value":"incident","show_logic":1,"order":1,"uuid":"252f708b-8d9ac576-68273bc77f50b5.16727897"}],"_parameters":{"textarea":{"regex":{"regex":"","fieldname":"regex","uuid":"252f708b-8d9ac576-68273a2d30ee81.22889005"},"range":{"range_min":10,"range_max":0,"fieldname":"range","uuid":"252f708b-8d9ac576-68273a2d317288.43530598"}}}},{"name":"Evidências","fieldtype":"file","required":0,"show_empty":0,"default_values":null,"itemtype":"","values":null,"description":"&#60;p&#62;Se possível, insira um print da tela ou imagem que ilustre a falha/incidente&#60;/p&#62;","row":3,"col":0,"width":4,"show_rule":2,"uuid":"252f708b-8d9ac576-68273a2d31a688.98554155","_conditions":[{"itemtype":"PluginFormcreatorQuestion","plugin_formcreator_questions_id":"252f708b-8d9ac576-68273a2d2ec115.84967052","show_condition":1,"show_value":"incident","show_logic":1,"order":1,"uuid":"252f708b-8d9ac576-68273cd36e0950.18415285"}],"_parameters":[]}],"_conditions":[{"itemtype":"PluginFormcreatorSection","plugin_formcreator_questions_id":"252f708b-8d9ac576-68273a2d2b1689.00438115","show_condition":1,"show_value":"Meu usuário","show_logic":1,"order":1,"uuid":"252f708b-8d9ac576-68273a2d39b5a9.97925699"},{"itemtype":"PluginFormcreatorSection","plugin_formcreator_questions_id":"252f708b-8d9ac576-68273a2d2b7994.82222056","show_condition":2,"show_value":"","show_logic":2,"order":2,"uuid":"252f708b-8d9ac576-68273a2d39e772.14204543"}]}],"_conditions":[],"_targets":{"PluginFormcreatorTargetTicket":[{"name":"Outros","target_name":"Outros","source_rule":1,"source_question":7,"type_rule":2,"type_question":"252f708b-8d9ac576-68273a2d2ec115.84967052","content":"##FULLFORM##","due_date_rule":0,"due_date_question":0,"due_date_value":-30,"due_date_period":1,"urgency_rule":1,"urgency_question":0,"validation_followup":1,"destination_entity":1,"destination_entity_value":0,"tag_type":1,"tag_questions":"","tag_specifics":"","category_rule":1,"category_question":0,"associate_rule":1,"associate_question":0,"location_rule":1,"location_question":0,"commonitil_validation_rule":1,"commonitil_validation_question":0,"show_rule":1,"sla_rule":1,"sla_question_tto":0,"sla_question_ttr":0,"ola_rule":1,"ola_question_tto":0,"ola_question_ttr":0,"uuid":"252f708b-8d9ac576-68273d06143ed0.13451637","_tickettemplate":"","_actors":[{"itemtype":"PluginFormcreatorTargetTicket","actor_role":1,"actor_type":1,"actor_value":0,"use_notification":1,"uuid":"252f708b-8d9ac576-68273d0614c015.75010861"},{"itemtype":"PluginFormcreatorTargetTicket","actor_role":2,"actor_type":2,"actor_value":0,"use_notification":1,"uuid":"252f708b-8d9ac576-68273d06150e49.05152258"}],"_ticket_relations":[],"_conditions":[]}],"PluginFormcreatorTargetChange":[],"PluginFormcreatorTargetProblem":[]},"_validators":[],"_translations":[]}]}